aiorelational/__init__.py
aiorelational/py.typed
aiorelational-0.9.0.dist-info/METADATA
aiorelational-0.9.0.dist-info/WHEEL
aiorelational-0.9.0.dist-info/RECORD
