Metadata-Version: 2.1
Name: aiorelational
Version: 0.9.0
Summary: Relational operators for working with Async iterators
Home-page: https://github.com/willemt/aiorelational
License: MIT
Keywords: asyncio
Author: Willem Thiart
Author-email: himself@willemthiart.com
Requires-Python: >=3.7,<4.0
Classifier: License :: OSI Approved :: MIT License
Classifier: Programming Language :: Python :: 3
Classifier: Programming Language :: Python :: 3.7
Classifier: Programming Language :: Python :: 3.8
Classifier: Programming Language :: Python :: 3.9
Classifier: Programming Language :: Python :: 3.10
Classifier: Programming Language :: Python :: 3.11
Classifier: Programming Language :: Python :: 3.12
Classifier: Topic :: Software Development :: Libraries :: Python Modules
Project-URL: Repository, https://github.com/willemt/aiorelational
